checker/__init__.py
checker/country_flags.py
checker/entitlements.py
checker/errors.py
apple_checker-0.5.8.dist-info/METADATA
apple_checker-0.5.8.dist-info/WHEEL
apple_checker-0.5.8.dist-info/top_level.txt
apple_checker-0.5.8.dist-info/RECORD
