Metadata-Version: 2.2
Name: apple-checker
Version: 0.5.8
Summary: A package for checking certificates and entitlements
Author: KupQ
Classifier: Programming Language :: Python :: 3
Classifier: License :: OSI Approved :: MIT License
Classifier: Operating System :: OS Independent
Requires-Python: >=3.6
Requires-Dist: cryptography
Requires-Dist: requests
Dynamic: author
Dynamic: classifier
Dynamic: description-content-type
Dynamic: requires-dist
Dynamic: requires-python
Dynamic: summary
